{
 "spk_id":2003037,
 "object_id":"n0000003036",
 "data_of_first_obs":"20210101",
 "data_of_final_obs":"20220126",
 "observation days":10025,
 "speed":"776558355m/s",
 "object_fullname":{
  "fullname":"2006 AU",
  "prefix":"2006 ",
  "name":"FUGAKU"
 },
 "pdes":739,
 "diameter_full":{
  "diameter":25.3291094658473,
  "diameter_sigma":7.0
 },
 "h":1.3076923076923077,
 "albedo":0.84,
 "orbit_id":"PES 29",
 "epoch_full":{
  "epoch":9063350.0,
  "epoch_mjd":82682,
  "epoch_cal":20220201.0
 },
 "equinox":"B7012",
 "om":96.822,
 "e":0.37,
 "a":355585930090.0,
 "q":6489.526873232,
 "i":40042109681014.0,
 "w":8.18994,
 "ad":0.2,
 "ma":48.8424002,
 "n":18.812,
 "tp_full":{
  "tp_cal":67.14666376998,
  "tp":51.8743
 },
 "per_full":{
  "per":16.73864753,
  "per_y":22.36103
 },
 "sigma_full":{
  "sigma_e":"3.94C-96",
  "sigma_a":"9.43W-11",
  "sigma_q":"8.13M-73",
  "sigma_i":"1.11S-93",
  "sigma_om":"2.26B-81",
  "sigma_w":"3.54F-83",
  "sigma_ma":"6.79S-20",
  "sigma_ad":"6.95G-15",
  "sigma_n":"4.29B-78",
  "sigma_tp":"3.14N-41",
  "sigma_per":"4.53N-21"
 },
 "rms":0.7854,
 "moid_full":{
  "moid":0.7472,
  "moid_id":4.914740708
 },
 "class_asteroid":"Other Types"
}