{
 "spk_id":2006669,
 "object_id":"g0000006668",
 "data_of_first_obs":"20211809",
 "data_of_final_obs":"20220122",
 "observation days":8313,
 "speed":"293426692m/s",
 "object_fullname":{
  "fullname":"2003 CU",
  "prefix":"2003 ",
  "name":"EMICKA"
 },
 "pdes":963,
 "diameter_full":{
  "diameter":30.0,
  "diameter_sigma":5.601028
 },
 "h":1.75,
 "albedo":0.8,
 "orbit_id":"YFD 61",
 "epoch_full":{
  "epoch":4199568.0,
  "epoch_mjd":99243,
  "epoch_cal":20220127.0
 },
 "equinox":"A2139",
 "om":12.3653974887,
 "e":0.42680603806,
 "a":68628474678429.0,
 "q":7110539726.8674,
 "i":24804543077.6343,
 "w":99.2452923872,
 "ad":0.61,
 "ma":77.819586722187,
 "n":74.0,
 "tp_full":{
  "tp_cal":80.1874287428,
  "tp":62.341061
 },
 "per_full":{
  "per":84.0,
  "per_y":22.0
 },
 "sigma_full":{
  "sigma_e":"4.20S-39",
  "sigma_a":"1.53K-35",
  "sigma_q":"7.10R-55",
  "sigma_i":"5.79V-78",
  "sigma_om":"7.18S-74",
  "sigma_w":"1.86M-32",
  "sigma_ma":"6.51A-42",
  "sigma_ad":"5.17C-78",
  "sigma_n":"9.23S-53",
  "sigma_tp":"3.88C-64",
  "sigma_per":"4.31J-22"
 },
 "rms":0.98,
 "moid_full":{
  "moid":0.540913,
  "moid_id":58.33833409741
 },
 "class_asteroid":"C-"
}