{
 "spk_id":2004474,
 "object_id":"r0000004473",
 "data_of_first_obs":"20210101",
 "data_of_final_obs":"20220126",
 "observation days":10025,
 "speed":"397075364m/s",
 "object_fullname":{
  "fullname":"2001 MA",
  "prefix":"2001 ",
  "name":"COTUR"
 },
 "pdes":204,
 "diameter_full":{
  "diameter":36.55010584952,
  "diameter_sigma":5.2197
 },
 "h":3.0,
 "albedo":0.78163,
 "orbit_id":"SHR 60",
 "epoch_full":{
  "epoch":8541413.0,
  "epoch_mjd":51043,
  "epoch_cal":20220204.0
 },
 "equinox":"S7643",
 "om":41.412366,
 "e":0.8,
 "a":140803167.335,
 "q":1130.41036,
 "i":437185.44076,
 "w":12.13931761258534,
 "ad":0.0,
 "ma":18.76,
 "n":56.14677351056,
 "tp_full":{
  "tp_cal":5.1,
  "tp":96.4604948474601
 },
 "per_full":{
  "per":67.582929853,
  "per_y":12.2829494
 },
 "sigma_full":{
  "sigma_e":"1.13P-21",
  "sigma_a":"3.46D-24",
  "sigma_q":"2.42C-95",
  "sigma_i":"2.60G-39",
  "sigma_om":"8.82G-26",
  "sigma_w":"4.76E-13",
  "sigma_ma":"5.47F-44",
  "sigma_ad":"3.33R-94",
  "sigma_n":"8.32V-87",
  "sigma_tp":"4.63E-95",
  "sigma_per":"1.82D-15"
 },
 "rms":0.0,
 "moid_full":{
  "moid":0.90472,
  "moid_id":12.498438
 },
 "class_asteroid":"Other Types"
}