{
 "spk_id":2003418,
 "object_id":"c0000003417",
 "data_of_first_obs":"20211809",
 "data_of_final_obs":"20220122",
 "observation days":8313,
 "speed":"39942062m/s",
 "object_fullname":{
  "fullname":"2007 SU",
  "prefix":"2007 ",
  "name":"BEITA"
 },
 "pdes":378,
 "diameter_full":{
  "diameter":4.482553,
  "diameter_sigma":8.256912
 },
 "h":1.4444444444444444,
 "albedo":0.326758,
 "orbit_id":"EIR 33",
 "epoch_full":{
  "epoch":8488671.0,
  "epoch_mjd":75696,
  "epoch_cal":20220131.0
 },
 "equinox":"C5893",
 "om":70.761663243187,
 "e":0.85324,
 "a":172929.874,
 "q":72961573894.99,
 "i":722396.1235332,
 "w":30.0,
 "ad":0.7253,
 "ma":23.89470858,
 "n":81.6,
 "tp_full":{
  "tp_cal":81.85469,
  "tp":39.3932970121853
 },
 "per_full":{
  "per":56.168928,
  "per_y":92.42
 },
 "sigma_full":{
  "sigma_e":"9.91T-40",
  "sigma_a":"7.86M-54",
  "sigma_q":"8.67S-80",
  "sigma_i":"2.30I-67",
  "sigma_om":"8.52T-46",
  "sigma_w":"1.38D-89",
  "sigma_ma":"2.66A-36",
  "sigma_ad":"8.21S-60",
  "sigma_n":"9.95P-38",
  "sigma_tp":"9.93A-94",
  "sigma_per":"1.91C-94"
 },
 "rms":0.5718,
 "moid_full":{
  "moid":0.0,
  "moid_id":63.67701
 },
 "class_asteroid":"Other Types"
}