{
 "spk_id":2002627,
 "object_id":"m0000002626",
 "data_of_first_obs":"20211809",
 "data_of_final_obs":"20220122",
 "observation days":8313,
 "speed":"586115645m/s",
 "object_fullname":{
  "fullname":"2005 LO",
  "prefix":"2005 ",
  "name":"CASTELLO"
 },
 "pdes":791,
 "diameter_full":{
  "diameter":65.36274,
  "diameter_sigma":6.35877
 },
 "h":1.0,
 "albedo":0.5312,
 "orbit_id":"ROI 17",
 "epoch_full":{
  "epoch":3426280.0,
  "epoch_mjd":68178,
  "epoch_cal":20220217.0
 },
 "equinox":"O5613",
 "om":2.88455838341,
 "e":0.0,
 "a":3.95478,
 "q":5.3484043458801,
 "i":7224994.662243,
 "w":52.43,
 "ad":0.0,
 "ma":37.0,
 "n":46.40702139,
 "tp_full":{
  "tp_cal":57.959,
  "tp":33.84649725
 },
 "per_full":{
  "per":2.7721798979,
  "per_y":57.988692862159
 },
 "sigma_full":{
  "sigma_e":"5.48D-57",
  "sigma_a":"9.16E-89",
  "sigma_q":"5.56M-33",
  "sigma_i":"1.66P-96",
  "sigma_om":"1.37S-62",
  "sigma_w":"6.64S-26",
  "sigma_ma":"8.57M-40",
  "sigma_ad":"9.57A-95",
  "sigma_n":"6.58O-97",
  "sigma_tp":"3.61S-80",
  "sigma_per":"1.41C-86"
 },
 "rms":0.66,
 "moid_full":{
  "moid":0.726,
  "moid_id":53.46803621797
 },
 "class_asteroid":"S-"
}