{
 "spk_id":2002194,
 "object_id":"v0000002193",
 "data_of_first_obs":"20211809",
 "data_of_final_obs":"20220122",
 "observation days":8313,
 "speed":"32944157m/s",
 "object_fullname":{
  "fullname":"2009 SE",
  "prefix":"2009 ",
  "name":"ANNELIESE"
 },
 "pdes":733,
 "diameter_full":{
  "diameter":82.5,
  "diameter_sigma":1.945
 },
 "h":1.2857142857142858,
 "albedo":0.1,
 "orbit_id":"PLE 81",
 "epoch_full":{
  "epoch":8934327.0,
  "epoch_mjd":97487,
  "epoch_cal":20220210.0
 },
 "equinox":"F7233",
 "om":33.28230569,
 "e":0.0,
 "a":8744384.702695,
 "q":4990267.9107,
 "i":49551.9,
 "w":76.3035477695339,
 "ad":0.603,
 "ma":96.438,
 "n":2.32156098914788,
 "tp_full":{
  "tp_cal":74.71763425,
  "tp":45.65815
 },
 "per_full":{
  "per":84.907418,
  "per_y":64.999
 },
 "sigma_full":{
  "sigma_e":"2.56G-11",
  "sigma_a":"6.84E-58",
  "sigma_q":"9.60E-80",
  "sigma_i":"7.25S-22",
  "sigma_om":"7.38W-21",
  "sigma_w":"1.13D-17",
  "sigma_ma":"4.36W-77",
  "sigma_ad":"9.90I-26",
  "sigma_n":"8.16L-53",
  "sigma_tp":"1.83S-25",
  "sigma_per":"8.43I-91"
 },
 "rms":0.200963646,
 "moid_full":{
  "moid":0.0,
  "moid_id":28.56137414638655
 },
 "class_asteroid":"Other Types"
}