{
 "spk_id":2009311,
 "object_id":"s0000009310",
 "data_of_first_obs":"20210101",
 "data_of_final_obs":"20220126",
 "observation days":10025,
 "speed":"574958036m/s",
 "object_fullname":{
  "fullname":"2020 GI",
  "prefix":"2020 ",
  "name":"JULIESMITH"
 },
 "pdes":958,
 "diameter_full":{
  "diameter":32.25990384686,
  "diameter_sigma":1.64704795578
 },
 "h":1.6,
 "albedo":0.0,
 "orbit_id":"TSC 90",
 "epoch_full":{
  "epoch":2092191.0,
  "epoch_mjd":85949,
  "epoch_cal":20220219.0
 },
 "equinox":"R6053",
 "om":14.16392128,
 "e":0.27268914576,
 "a":81312072.7552,
 "q":26943360.2,
 "i":774889734469074.0,
 "w":79.2,
 "ad":0.6209,
 "ma":20.7576521505,
 "n":14.18698678188,
 "tp_full":{
  "tp_cal":23.43,
  "tp":98.7036584
 },
 "per_full":{
  "per":6.46743,
  "per_y":83.0
 },
 "sigma_full":{
  "sigma_e":"5.17A-11",
  "sigma_a":"1.36B-71",
  "sigma_q":"8.65A-44",
  "sigma_i":"9.20W-29",
  "sigma_om":"5.25S-37",
  "sigma_w":"7.48H-15",
  "sigma_ma":"1.82A-49",
  "sigma_ad":"9.21A-67",
  "sigma_n":"4.83T-32",
  "sigma_tp":"7.88N-33",
  "sigma_per":"9.78W-45"
 },
 "rms":0.0,
 "moid_full":{
  "moid":0.62,
  "moid_id":64.35016
 },
 "class_asteroid":"M-types"
}