{
 "spk_id":2002189,
 "object_id":"b0000002188",
 "data_of_first_obs":"20211809",
 "data_of_final_obs":"20220122",
 "observation days":8313,
 "speed":"885221850m/s",
 "object_fullname":{
  "fullname":"2018 MA",
  "prefix":"2018 ",
  "name":"CHANCO"
 },
 "pdes":790,
 "diameter_full":{
  "diameter":9.1062,
  "diameter_sigma":2.5051351857
 },
 "h":0.4,
 "albedo":0.5,
 "orbit_id":"PFR 71",
 "epoch_full":{
  "epoch":3526550.0,
  "epoch_mjd":21347,
  "epoch_cal":20220212.0
 },
 "equinox":"N2018",
 "om":25.5059946692,
 "e":0.262,
 "a":453696448119.0,
 "q":3606607782582.27,
 "i":543375802862888.0,
 "w":4.4826852935178,
 "ad":0.6192032,
 "ma":4.0,
 "n":52.57,
 "tp_full":{
  "tp_cal":83.96480445,
  "tp":36.867234804694
 },
 "per_full":{
  "per":30.11384397728,
  "per_y":52.81709453
 },
 "sigma_full":{
  "sigma_e":"9.53T-26",
  "sigma_a":"7.27I-21",
  "sigma_q":"1.77O-66",
  "sigma_i":"8.25O-22",
  "sigma_om":"2.99B-72",
  "sigma_w":"9.43C-70",
  "sigma_ma":"6.69M-69",
  "sigma_ad":"6.79M-74",
  "sigma_n":"4.51L-16",
  "sigma_tp":"1.81R-80",
  "sigma_per":"3.50E-74"
 },
 "rms":0.52305,
 "moid_full":{
  "moid":0.73,
  "moid_id":89.2852925799
 },
 "class_asteroid":"Other Types"
}