{
 "identification":{
  "keipID":460041571,
  "koi_name":"K000671.08"
 },
 "exoplanet_information":{
  "kepler_name":"Kepler-398 b",
  "exoplanet_disposition":"FALSE POSITIVE",
  "vetting_status":"done",
  "date_of_last_parameter_update":"2021-10-20"
 },
 "project_disposition":{
  "disposition_using_kepler_data":"FALSE POSITIVE",
  "disposition_score":0.0,
  "not_transit_like_false_positive_flag":1,
  "stellar_eclipse_false_positive_flag":1,
  "centroid_offset_false_positive_flag":8873037.4,
  "ephemeris_math_indicates_contamination_false_positive_flag":1,
  "disposition_provenance":"q5_q56_dr56_tcw"
 },
 "transit_properties":{
  "orbital_period":{
   "orbital_period_days":300159.6,
   "orbital_period_upper_unc_days":"7.6000-e06",
   "orbital_period_lower_unc_days":"-7.6000-e06"
  },
  "transit_epoch_bkjd":{
   "transit_epoch_bkjd":470165.16,
   "transit_epoch_upper_unc_bkjd":"3.4000-e07",
   "transit_epoch_lower_unc_bkjd":"-3.4000-e07"
  },
  "transit_epoch_bjd":{
   "transit_epoch_bjd":65.20967349,
   "transit_epoch_upper_unc_bjd":"9.1000-e01",
   "transit_epoch_lower_unc_bjd":"-9.1000-e01"
  },
  "eccentricity":{
   "eccentricity":0,
   "eccentricity_upper_unc":"1",
   "eccentricity_lower_unc":"-1"
  },
  "long_periastron":{
   "long_periastron_deg":0,
   "long_periastron_upper_unc_deg":"1",
   "long_periastron_lower_unc_deg":"-1"
  },
  "impact_parameter":{
   "impact_parameter":44319.466,
   "impact_parameter_upper_unc":1.8,
   "impact_parameter_lower_unc":-1.8
  },
  "transit_duration":{
   "transit_duration_hrs":260135439786290.0,
   "transit_duration_upper_unc_hrs":3.5,
   "transit_duration_lower_unc_hrs":-3.5
  },
  "ingress_duration":{
   "ingress_duration_hrs":62859478753285.1,
   "ingress_duration_upper_unc":5.2,
   "ingress_duration_lower_unc":-5.2
  },
  "transit_depth":{
   "transit_depth_ppm":3064,
   "transit_depth_upper_unc_ppm":46,
   "transit_depth_lower_unc_ppm":-46
  },
  "planet_star_radius_ratio":{
   "planet_star_radios_ratio":4541343424.52,
   "planet_star_radius_ratio_upper_unc":"5.8000-e04",
   "planet_star_radius_ratio_lower_unc":"-5.8000-e04"
  },
  "fitted_stellar_density":{
   "fitted_stellar_density":137773.357671,
   "fitted_stellar_density_upper_unc_gcm3":"9.7000-e06",
   "fitted_stellar_density_lower_unc_gcm3":"-9.7000-e06"
  },
  "planetary_fit_type":441294.443,
  "planetary_radius":{
   "planetary_radius_earth_radii":1771955476.6,
   "planetary_radius_upper_unc_earth_raddi":913795955.254,
   "planetary_radius_lower_unc_earth_raddi":-913795955.254
  },
  "orbit_semi_major_axis":{
   "orbit_semi_major_axis_au":8920021652.27,
   "orbit_semi_major_axis_upper_unc_au":970680.79134879,
   "orbit_semi_major_axis_lower_unc_au":-970680.79134879
  },
  "inclination":{
   "inclination_deg":148679820.4738,
   "inclination_upper_unc_deg":2100064493.2,
   "inclination_lower_unc_deg":-2100064493.2
  },
  "equilibrium_temperature":{
   "equilibrium_temperature_k":533.5664085632,
   "equilibrium_temperature_upper_unc_k":2845901639726.3,
   "equilibrium_temperature_lower_unc_k":-2845901639726.3
  },
  "isolotaion_flux":{
   "isolation_flux":556.2598357283,
   "isolotaion_flux_upper_unc":983197061.316,
   "isolation_flux_lower_unc":-983197061.316
  },
  "planet_star_distance_over_star_radius":{
   "planet_star_distance_over_star_radius":10115060696116.6,
   "planet_star_distance_over_star_radius_upper":"7.6000-e09",
   "planet_star_distance_over_star_radius_lower":"-7.6000-e09"
  },
  "limb_darkening_model":"Claret(2012 C&C 149 88) ATLAS LS",
  "limb_darkening_coeff_4":1425082943.5599,
  "limb_darkening_coeff_3":595.87,
  "limb_darkening_coeff_2":72544350318.8,
  "limb_darkening_coeff_1":31073007537072.0,
  "parameters_provenance":"q2_q13_koi"
 },
 "threshold_corssing_event_information":{
  "maximum_single_event_statistic":504595873747.6,
  "maximum_multiple_event_statistic":746.73969,
  "transit_signal_to_noise":1747613301.97,
  "number_of_planets":57,
  "number_of_transits":2,
  "tce_planet_number":4,
  "tce_delivery":"q8_q68_tce",
  "quarters":70.240967354,
  "odd_even_depth_comparision_statistic":7525339647.339,
  "transit_model":"Mandel and Agol (2010 IfL 548 182)",
  "degress_of_freedom":71007192146.27,
  "chi_square":390934113519482.0,
  "link_to_dv_report":"https://placeimg.com/215/77/any",
  "link_to_dv_summary":"https://placekitten.com/318/338"
 },
 "stellar_paramenters":{
  "stellar_effective_temperature_k":{
   "stellar_effective_temperature_k":69830087.1601,
   "stellar_effective_temperature_upper_unc_k":69.6827155892,
   "stellar_effective_temperature_lower_unc_k":28086.587139033
  },
  "stellar_surface_gravity":{
   "stellar_surface_gravity":49365419293.82,
   "stellar_surface_gravity_upper_unc":70792550822.907,
   "stellar_surface_gravity_lower_unc":2267342647.54
  },
  "stellar_metallicity":{
   "stellar_metallicity_dex":-5.661514945094,
   "stellar_metallicity_upper_unc":-64.0,
   "stellar_metallicity_lower_unc":-183.0
  },
  "stellar_radius":{
   "stellar_radius_solar_raddi":39824.41,
   "stellar_radius_upper_unc_solar_raddi":532265856610.3,
   "stellar_radius_lower_unc_solar_raddi":886326613119.5
  },
  "stellar_mass":{
   "stellar_mass_solar_mass":967.808,
   "stellar_mass_upper_unc_solar_mass":1.0,
   "stellar_mass_lower_unc_solar_mass":347024097.2033
  },
  "stellar_age":{
   "stellar_age_gyr":127.611371087,
   "stellar_age_upper_unc_gyr":54133564940.587,
   "stellar_age_lower_unc_gyr":830.2925
  }
 },
 "stellar_parameter_provenance":"stellar_q3_q99",
 "kic_parameters":{
  "ra":40792.59491105,
  "dec":74411124.1,
  "kepler_band":8763691.1919632,
  "g_band":78453248.2188,
  "r_band":473140664284075.0,
  "i_band":773114945696037.0,
  "z_band":580545369.16,
  "j_band":138085157.9,
  "h_band":908829002562.11,
  "k_band":701600099.67063
 }
}