{
 "identification":{
  "keipID":636859375,
  "koi_name":"K000635.09"
 },
 "exoplanet_information":{
  "kepler_name":"Kepler-1702 r",
  "exoplanet_disposition":"FALSE POSITIVE",
  "vetting_status":"done",
  "date_of_last_parameter_update":"2020-05-10"
 },
 "project_disposition":{
  "disposition_using_kepler_data":"FALSE POSITIVE",
  "disposition_score":1.0,
  "not_transit_like_false_positive_flag":1,
  "stellar_eclipse_false_positive_flag":1,
  "centroid_offset_false_positive_flag":2693911733010.37,
  "ephemeris_math_indicates_contamination_false_positive_flag":1,
  "disposition_provenance":"q3_q10_dr10_tcp"
 },
 "transit_properties":{
  "orbital_period":{
   "orbital_period_days":4557337092.9,
   "orbital_period_upper_unc_days":"9.7000-e03",
   "orbital_period_lower_unc_days":"-9.7000-e03"
  },
  "transit_epoch_bkjd":{
   "transit_epoch_bkjd":95.0,
   "transit_epoch_upper_unc_bkjd":"1.3000-e04",
   "transit_epoch_lower_unc_bkjd":"-1.3000-e04"
  },
  "transit_epoch_bjd":{
   "transit_epoch_bjd":29676.0,
   "transit_epoch_upper_unc_bjd":"8.6000-e07",
   "transit_epoch_lower_unc_bjd":"-8.6000-e07"
  },
  "eccentricity":{
   "eccentricity":1,
   "eccentricity_upper_unc":"0",
   "eccentricity_lower_unc":"-0"
  },
  "long_periastron":{
   "long_periastron_deg":1,
   "long_periastron_upper_unc_deg":"0",
   "long_periastron_lower_unc_deg":"-0"
  },
  "impact_parameter":{
   "impact_parameter":6332767103509.0,
   "impact_parameter_upper_unc":7.7,
   "impact_parameter_lower_unc":-7.7
  },
  "transit_duration":{
   "transit_duration_hrs":399500.7031,
   "transit_duration_upper_unc_hrs":1.5,
   "transit_duration_lower_unc_hrs":-1.5
  },
  "ingress_duration":{
   "ingress_duration_hrs":10025694257809.0,
   "ingress_duration_upper_unc":8.4,
   "ingress_duration_lower_unc":-8.4
  },
  "transit_depth":{
   "transit_depth_ppm":3835,
   "transit_depth_upper_unc_ppm":32,
   "transit_depth_lower_unc_ppm":-32
  },
  "planet_star_radius_ratio":{
   "planet_star_radios_ratio":292160760.1,
   "planet_star_radius_ratio_upper_unc":"4.8000-e05",
   "planet_star_radius_ratio_lower_unc":"-4.8000-e05"
  },
  "fitted_stellar_density":{
   "fitted_stellar_density":21.96127,
   "fitted_stellar_density_upper_unc_gcm3":"7.8000-e06",
   "fitted_stellar_density_lower_unc_gcm3":"-7.8000-e06"
  },
  "planetary_fit_type":64335017606.9,
  "planetary_radius":{
   "planetary_radius_earth_radii":5832.0,
   "planetary_radius_upper_unc_earth_raddi":2066018.32,
   "planetary_radius_lower_unc_earth_raddi":-2066018.32
  },
  "orbit_semi_major_axis":{
   "orbit_semi_major_axis_au":562.758687,
   "orbit_semi_major_axis_upper_unc_au":864523405.9245,
   "orbit_semi_major_axis_lower_unc_au":-864523405.9245
  },
  "inclination":{
   "inclination_deg":327009380.23,
   "inclination_upper_unc_deg":6197007.934,
   "inclination_lower_unc_deg":-6197007.934
  },
  "equilibrium_temperature":{
   "equilibrium_temperature_k":4289512.60296325,
   "equilibrium_temperature_upper_unc_k":1429478.81,
   "equilibrium_temperature_lower_unc_k":-1429478.81
  },
  "isolotaion_flux":{
   "isolation_flux":557094064.872129,
   "isolotaion_flux_upper_unc":430910837.54824,
   "isolation_flux_lower_unc":-430910837.54824
  },
  "planet_star_distance_over_star_radius":{
   "planet_star_distance_over_star_radius":88065315211723.0,
   "planet_star_distance_over_star_radius_upper":"3.8000-e07",
   "planet_star_distance_over_star_radius_lower":"-3.8000-e07"
  },
  "limb_darkening_model":"Claret(2020 C&D 208 50) ATLAS NC",
  "limb_darkening_coeff_4":6384794788541.0,
  "limb_darkening_coeff_3":2004347241.0,
  "limb_darkening_coeff_2":262.0,
  "limb_darkening_coeff_1":145353368199084.0,
  "parameters_provenance":"q5_q17_kepler"
 },
 "threshold_corssing_event_information":{
  "maximum_single_event_statistic":932212476.917267,
  "maximum_multiple_event_statistic":54799170179.8,
  "transit_signal_to_noise":8487551265.0,
  "number_of_planets":66,
  "number_of_transits":7,
  "tce_planet_number":1,
  "tce_delivery":"q8_q46_tce",
  "quarters":406066955.12278,
  "odd_even_depth_comparision_statistic":31293555737627.0,
  "transit_model":"Mandel and Agol (2012 AgD 658 763)",
  "degress_of_freedom":5024638357653.0,
  "chi_square":8211207342.406,
  "link_to_dv_report":"https://www.lorempixel.com/802/519",
  "link_to_dv_summary":"https://placeimg.com/1016/581/any"
 },
 "stellar_paramenters":{
  "stellar_effective_temperature_k":{
   "stellar_effective_temperature_k":306431509413.4,
   "stellar_effective_temperature_upper_unc_k":21080818667158.8,
   "stellar_effective_temperature_lower_unc_k":922767088.75
  },
  "stellar_surface_gravity":{
   "stellar_surface_gravity":44570226372617.0,
   "stellar_surface_gravity_upper_unc":71.164,
   "stellar_surface_gravity_lower_unc":132321299.34
  },
  "stellar_metallicity":{
   "stellar_metallicity_dex":46396307278.4868,
   "stellar_metallicity_upper_unc":532371.520333657,
   "stellar_metallicity_lower_unc":20.6520327246
  },
  "stellar_radius":{
   "stellar_radius_solar_raddi":71098280.92605,
   "stellar_radius_upper_unc_solar_raddi":3209550.781,
   "stellar_radius_lower_unc_solar_raddi":334.56213924
  },
  "stellar_mass":{
   "stellar_mass_solar_mass":964638.4,
   "stellar_mass_upper_unc_solar_mass":610.708106415,
   "stellar_mass_lower_unc_solar_mass":894835369.468
  },
  "stellar_age":{
   "stellar_age_gyr":8614390.988,
   "stellar_age_upper_unc_gyr":42708692037.53,
   "stellar_age_lower_unc_gyr":3052406037303.0
  }
 },
 "stellar_parameter_provenance":"stellar_q1_q65",
 "kic_parameters":{
  "ra":1827247142474.4,
  "dec":35706531402.4,
  "kepler_band":2.1694538,
  "g_band":3943.85131743,
  "r_band":7642524.51505,
  "i_band":482867492656129.0,
  "z_band":2950879.43682019,
  "j_band":61.646698,
  "h_band":7.0,
  "k_band":33.0
 }
}