{
 "identification":{
  "keipID":321466498,
  "koi_name":"K000214.06"
 },
 "exoplanet_information":{
  "kepler_name":"Kepler-1257 r",
  "exoplanet_disposition":"FALSE POSITIVE",
  "vetting_status":"done",
  "date_of_last_parameter_update":"2020-11-20"
 },
 "project_disposition":{
  "disposition_using_kepler_data":"NOT DISPOSITIONED",
  "disposition_score":8.0,
  "not_transit_like_false_positive_flag":1,
  "stellar_eclipse_false_positive_flag":0,
  "centroid_offset_false_positive_flag":0.992645,
  "ephemeris_math_indicates_contamination_false_positive_flag":0,
  "disposition_provenance":"q2_q13_dr40_tce"
 },
 "transit_properties":{
  "orbital_period":{
   "orbital_period_days":734732279.97022,
   "orbital_period_upper_unc_days":"7.2000-e09",
   "orbital_period_lower_unc_days":"-7.2000-e09"
  },
  "transit_epoch_bkjd":{
   "transit_epoch_bkjd":2378100.90971987,
   "transit_epoch_upper_unc_bkjd":"5.5000-e08",
   "transit_epoch_lower_unc_bkjd":"-5.5000-e08"
  },
  "transit_epoch_bjd":{
   "transit_epoch_bjd":5784.7668033,
   "transit_epoch_upper_unc_bjd":"8.7000-e05",
   "transit_epoch_lower_unc_bjd":"-8.7000-e05"
  },
  "eccentricity":{
   "eccentricity":0,
   "eccentricity_upper_unc":"1",
   "eccentricity_lower_unc":"-1"
  },
  "long_periastron":{
   "long_periastron_deg":0,
   "long_periastron_upper_unc_deg":"1",
   "long_periastron_lower_unc_deg":"-1"
  },
  "impact_parameter":{
   "impact_parameter":46349139880756.9,
   "impact_parameter_upper_unc":8.7,
   "impact_parameter_lower_unc":-8.7
  },
  "transit_duration":{
   "transit_duration_hrs":7589802072.8,
   "transit_duration_upper_unc_hrs":2.7,
   "transit_duration_lower_unc_hrs":-2.7
  },
  "ingress_duration":{
   "ingress_duration_hrs":2395296118955.6,
   "ingress_duration_upper_unc":0.9,
   "ingress_duration_lower_unc":-0.9
  },
  "transit_depth":{
   "transit_depth_ppm":7733,
   "transit_depth_upper_unc_ppm":33,
   "transit_depth_lower_unc_ppm":-33
  },
  "planet_star_radius_ratio":{
   "planet_star_radios_ratio":580719452318290.0,
   "planet_star_radius_ratio_upper_unc":"8.1000-e04",
   "planet_star_radius_ratio_lower_unc":"-8.1000-e04"
  },
  "fitted_stellar_density":{
   "fitted_stellar_density":6478041.851,
   "fitted_stellar_density_upper_unc_gcm3":"9.4000-e01",
   "fitted_stellar_density_lower_unc_gcm3":"-9.4000-e01"
  },
  "planetary_fit_type":133246084857953.0,
  "planetary_radius":{
   "planetary_radius_earth_radii":357872.508518918,
   "planetary_radius_upper_unc_earth_raddi":56936562.6,
   "planetary_radius_lower_unc_earth_raddi":-56936562.6
  },
  "orbit_semi_major_axis":{
   "orbit_semi_major_axis_au":33905418327972.0,
   "orbit_semi_major_axis_upper_unc_au":4275771967355.1,
   "orbit_semi_major_axis_lower_unc_au":-4275771967355.1
  },
  "inclination":{
   "inclination_deg":24076358570.2,
   "inclination_upper_unc_deg":58698.1157791,
   "inclination_lower_unc_deg":-58698.1157791
  },
  "equilibrium_temperature":{
   "equilibrium_temperature_k":774.79273,
   "equilibrium_temperature_upper_unc_k":73436624663.1064,
   "equilibrium_temperature_lower_unc_k":-73436624663.1064
  },
  "isolotaion_flux":{
   "isolation_flux":170686703109297.0,
   "isolotaion_flux_upper_unc":34.0,
   "isolation_flux_lower_unc":-34.0
  },
  "planet_star_distance_over_star_radius":{
   "planet_star_distance_over_star_radius":3004309527.0,
   "planet_star_distance_over_star_radius_upper":"2.2000-e08",
   "planet_star_distance_over_star_radius_lower":"-2.2000-e08"
  },
  "limb_darkening_model":"Claret(2003 B&E 577 82) ATLAS WK",
  "limb_darkening_coeff_4":43.79655,
  "limb_darkening_coeff_3":4687270715890.0,
  "limb_darkening_coeff_2":8636161707647.0,
  "limb_darkening_coeff_1":5173210698487.5,
  "parameters_provenance":"q1_q27_kepler"
 },
 "threshold_corssing_event_information":{
  "maximum_single_event_statistic":92.5728,
  "maximum_multiple_event_statistic":781631965335.9,
  "transit_signal_to_noise":52.206,
  "number_of_planets":89,
  "number_of_transits":1,
  "tce_planet_number":6,
  "tce_delivery":"q7_q50_tce",
  "quarters":819351136705501.0,
  "odd_even_depth_comparision_statistic":91190195048006.0,
  "transit_model":"Mandel and Agol (2000 HsS 567 193)",
  "degress_of_freedom":892888631440436.0,
  "chi_square":68.18139849,
  "link_to_dv_report":"https://www.lorempixel.com/2/843",
  "link_to_dv_summary":"https://www.lorempixel.com/903/21"
 },
 "stellar_paramenters":{
  "stellar_effective_temperature_k":{
   "stellar_effective_temperature_k":3.49355543421854,
   "stellar_effective_temperature_upper_unc_k":83.71,
   "stellar_effective_temperature_lower_unc_k":20784750382.3
  },
  "stellar_surface_gravity":{
   "stellar_surface_gravity":3.762719308,
   "stellar_surface_gravity_upper_unc":56861453227.75,
   "stellar_surface_gravity_lower_unc":1988.20575
  },
  "stellar_metallicity":{
   "stellar_metallicity_dex":-4602711321.0,
   "stellar_metallicity_upper_unc":-2277.565852482,
   "stellar_metallicity_lower_unc":730451837.0
  },
  "stellar_radius":{
   "stellar_radius_solar_raddi":9.76182136611,
   "stellar_radius_upper_unc_solar_raddi":66752.2916588132,
   "stellar_radius_lower_unc_solar_raddi":60215758.6
  },
  "stellar_mass":{
   "stellar_mass_solar_mass":69838636043.5426,
   "stellar_mass_upper_unc_solar_mass":0.40622262,
   "stellar_mass_lower_unc_solar_mass":158024813.8183
  },
  "stellar_age":{
   "stellar_age_gyr":891265.12,
   "stellar_age_upper_unc_gyr":197671.150398445,
   "stellar_age_lower_unc_gyr":165.3266423037
  }
 },
 "stellar_parameter_provenance":"stellar_q6_q53",
 "kic_parameters":{
  "ra":503245.5053,
  "dec":4.1481757661697,
  "kepler_band":514.21206079,
  "g_band":36.8291658103,
  "r_band":82.78,
  "i_band":1914619805.0,
  "z_band":20930.0,
  "j_band":9758687917.5,
  "h_band":32108.70447511,
  "k_band":2.574849
 }
}