{
 "TEST_REGISTRATION":"UBAP32135736831811",
 "NOTEBOOK":"GREEN",
 "STUDENT_DATA":{
  "NAME":"Wani Pertiwi",
  "GENDER":"F",
  "RACE":"MESTIZOS",
  "BIRTHDAY":"1957-01-03",
  "AGE":"64",
  "CIVIL_STATUS":"DIVORCED",
  "PHONE":"+62 (0227) 233 1189",
  "OCCUPATION":"STUDENT",
  "NU_IDENTIFICATION":"007-25-1771",
  "MAILER":"wan00@yahoo.com",
  "PATRONUS":"HERRING",
  "WAND":null
 },
 "SCHOOL_DATA":{
  "SCHOOL_REGISTRATION":"JBNR81685242549066",
  "SCHOOL":"UAGADOU",
  "COUNTRY":"AFRICA",
  "HOUSES":null
 },
 "EXAM_DATA":{
  "MEDIA":1109.86,
  "SUBJECTS":{
   "DIVINATION":95.0,
   "ALCHEMY":9.0,
   "APPARITION":34.0,
   "ARITHMANCY":87.0,
   "MUGGLE_ART":64.0,
   "DARK_ARTS":99.0,
   "ASTRONOMY":84.0,
   "DEFENSE_AGAINST_THE_DARK_ARTS":78.0,
   "STUDY_OF_ANCIENT_RUNES":75.0,
   "MUGGLE_STUDY":84.0,
   "ANCIENT_STUDIES":26.0,
   "ADVANCED_ARITHMANCY_STUDIES":99.0,
   "SPELLS":52.0,
   "HERBOLOGY":61.0,
   "HISTORY_OF_MAGIC":6.0,
   "DEFAULT":7.0,
   "POTIONS":59.0,
   "THEORY_OF_MAGIC":30.0,
   "TRANSFIGURATION":9.0,
   "CARE_OF_MAGICAL_CREATURES":81.0
  }
 }
}