{
 "TEST_REGISTRATION":"ECIF61623184747623",
 "NOTEBOOK":"GREEN",
 "STUDENT_DATA":{
  "NAME":"Akira Koizumi",
  "GENDER":"M",
  "RACE":"MESTIZOS",
  "BIRTHDAY":"1954-06-18",
  "AGE":"67",
  "CIVIL_STATUS":"WIDOWED",
  "PHONE":"080-1470-6217",
  "OCCUPATION":"Diplomatic Services operational officer",
  "NU_IDENTIFICATION":"307-38-9076",
  "MAILER":"a30@gmail.com",
  "PATRONUS":"HAWORTHIA COOPER",
  "WAND":"SKIN OF MOSAIC PLANT"
 },
 "SCHOOL_DATA":{
  "SCHOOL_REGISTRATION":"UBYC26544531189604",
  "SCHOOL":"MAHOUTOKORO",
  "COUNTRY":"JAPAN",
  "HOUSES":"HARU"
 },
 "EXAM_DATA":{
  "MEDIA":1118.05,
  "SUBJECTS":{
   "DIVINATION":20.0,
   "ALCHEMY":50.0,
   "APPARITION":10.0,
   "ARITHMANCY":61.0,
   "MUGGLE_ART":62.0,
   "DARK_ARTS":93.0,
   "ASTRONOMY":95.0,
   "DEFENSE_AGAINST_THE_DARK_ARTS":5.0,
   "STUDY_OF_ANCIENT_RUNES":80.0,
   "MUGGLE_STUDY":55.0,
   "ANCIENT_STUDIES":99.0,
   "ADVANCED_ARITHMANCY_STUDIES":85.0,
   "SPELLS":74.0,
   "HERBOLOGY":98.0,
   "HISTORY_OF_MAGIC":53.0,
   "DEFAULT":43.0,
   "POTIONS":26.0,
   "THEORY_OF_MAGIC":26.0,
   "TRANSFIGURATION":37.0,
   "CARE_OF_MAGICAL_CREATURES":43.0
  }
 }
}