{
 "TEST_REGISTRATION":"PZDM85787037150984",
 "NOTEBOOK":"BLUE",
 "STUDENT_DATA":{
  "NAME":"Devi Suryono",
  "GENDER":"F",
  "RACE":"HUMANS (MUGGLE)",
  "BIRTHDAY":"2000-01-21",
  "AGE":"21",
  "CIVIL_STATUS":"WIDOWED",
  "PHONE":"+62 (095) 083-9064",
  "OCCUPATION":"STUDENT",
  "NU_IDENTIFICATION":"320-14-9135",
  "MAILER":"dev320-14-@yahoo.com",
  "PATRONUS":"POT PLANT",
  "WAND":null
 },
 "SCHOOL_DATA":{
  "SCHOOL_REGISTRATION":"ORKM76932118402008",
  "SCHOOL":"UAGADOU",
  "COUNTRY":"AFRICA",
  "HOUSES":null
 },
 "EXAM_DATA":{
  "MEDIA":1084.33,
  "SUBJECTS":{
   "DIVINATION":61.0,
   "ALCHEMY":96.0,
   "APPARITION":11.0,
   "ARITHMANCY":77.0,
   "MUGGLE_ART":24.0,
   "DARK_ARTS":51.0,
   "ASTRONOMY":50.0,
   "DEFENSE_AGAINST_THE_DARK_ARTS":16.0,
   "STUDY_OF_ANCIENT_RUNES":85.0,
   "MUGGLE_STUDY":81.0,
   "ANCIENT_STUDIES":90.0,
   "ADVANCED_ARITHMANCY_STUDIES":79.0,
   "SPELLS":18.0,
   "HERBOLOGY":43.0,
   "HISTORY_OF_MAGIC":85.0,
   "DEFAULT":94.0,
   "POTIONS":13.0,
   "THEORY_OF_MAGIC":91.0,
   "TRANSFIGURATION":15.0,
   "CARE_OF_MAGICAL_CREATURES":28.0
  }
 }
}