{
 "TEST_REGISTRATION":"PYUX36126419015566",
 "NOTEBOOK":"BLUE",
 "STUDENT_DATA":{
  "NAME":"Monica Sanders",
  "GENDER":"F",
  "BIRTHDAY":"1926-08-29",
  "RACE":"MESTIZOS",
  "AGE":"95",
  "CIVIL_STATUS":"SINGLE",
  "PHONE":"090.499.4930",
  "OCCUPATION":"STUDENT",
  "NU_IDENTIFICATION":"726-54-3278",
  "MAILER":"moni726-54-3@gmail.com",
  "PATRONUS":"BARRACUDA",
  "WAND":"LIVER OF ANOPHELES"
 },
 "SCHOOL_DATA":{
  "SCHOOL_REGISTRATION":"CBUO29064886586475",
  "SCHOOL":"ILVERMORNY",
  "COUNTRY":"EUA",
  "HOUSES":"PUKWUDGIE"
 },
 "EXAM_DATA":{
  "MEDIA":961.57,
  "SUBJECTS":{
   "DIVINATION":83.0,
   "ALCHEMY":22.0,
   "APPARITION":60.0,
   "ARITHMANCY":8.0,
   "MUGGLE_ART":9.0,
   "DARK_ARTS":8.0,
   "ASTRONOMY":27.0,
   "DEFENSE_AGAINST_THE_DARK_ARTS":63.0,
   "STUDY_OF_ANCIENT_RUNES":24.0,
   "MUGGLE_STUDY":46.0,
   "ANCIENT_STUDIES":56.0,
   "ADVANCED_ARITHMANCY_STUDIES":82.0,
   "SPELLS":45.0,
   "HERBOLOGY":7.0,
   "HISTORY_OF_MAGIC":97.0,
   "DEFAULT":68.0,
   "POTIONS":61.0,
   "THEORY_OF_MAGIC":95.0,
   "TRANSFIGURATION":82.0,
   "CARE_OF_MAGICAL_CREATURES":33.0
  }
 }
}