{
 "TEST_REGISTRATION":"LFNP13723305962640",
 "NOTEBOOK":"RED",
 "STUDENT_DATA":{
  "NAME":"Rahmat Wibowo",
  "GENDER":"M",
  "RACE":"HUMANS (MUGGLE)",
  "BIRTHDAY":"1957-06-30",
  "AGE":"64",
  "CIVIL_STATUS":"DIVORCED",
  "PHONE":"+62 (53) 420 7085",
  "OCCUPATION":"STUDENT",
  "NU_IDENTIFICATION":"522-31-7061",
  "MAILER":"rahm522-31-70@hotmail.com",
  "PATRONUS":"COD",
  "WAND":null
 },
 "SCHOOL_DATA":{
  "SCHOOL_REGISTRATION":"WRQS83804397571851",
  "SCHOOL":"UAGADOU",
  "COUNTRY":"AFRICA",
  "HOUSES":null
 },
 "EXAM_DATA":{
  "MEDIA":683.67,
  "SUBJECTS":{
   "DIVINATION":15.0,
   "ALCHEMY":20.0,
   "APPARITION":11.0,
   "ARITHMANCY":30.0,
   "MUGGLE_ART":70.0,
   "DARK_ARTS":67.0,
   "ASTRONOMY":13.0,
   "DEFENSE_AGAINST_THE_DARK_ARTS":67.0,
   "STUDY_OF_ANCIENT_RUNES":3.0,
   "MUGGLE_STUDY":63.0,
   "ANCIENT_STUDIES":37.0,
   "ADVANCED_ARITHMANCY_STUDIES":23.0,
   "SPELLS":45.0,
   "HERBOLOGY":4.0,
   "HISTORY_OF_MAGIC":61.0,
   "DEFAULT":89.0,
   "POTIONS":2.0,
   "THEORY_OF_MAGIC":9.0,
   "TRANSFIGURATION":13.0,
   "CARE_OF_MAGICAL_CREATURES":98.0
  }
 }
}