{
 "TEST_REGISTRATION":"WQKD98290511841195",
 "NOTEBOOK":"RED",
 "STUDENT_DATA":{
  "NAME":"Simon Maheswara",
  "GENDER":"M",
  "RACE":"MESTIZOS",
  "BIRTHDAY":"1923-11-11",
  "AGE":"98",
  "CIVIL_STATUS":"SINGLE",
  "PHONE":"(098) 072-6974",
  "OCCUPATION":"STUDENT",
  "NU_IDENTIFICATION":"885-12-1634",
  "MAILER":"sim885-12-16@hotmail.com",
  "PATRONUS":"ANOPHELES",
  "WAND":null
 },
 "SCHOOL_DATA":{
  "SCHOOL_REGISTRATION":"XVUF28095503720017",
  "SCHOOL":"UAGADOU",
  "COUNTRY":"AFRICA",
  "HOUSES":null
 },
 "EXAM_DATA":{
  "MEDIA":779.52,
  "SUBJECTS":{
   "DIVINATION":13.0,
   "ALCHEMY":13.0,
   "APPARITION":22.0,
   "ARITHMANCY":41.0,
   "MUGGLE_ART":73.0,
   "DARK_ARTS":38.0,
   "ASTRONOMY":55.0,
   "DEFENSE_AGAINST_THE_DARK_ARTS":8.0,
   "STUDY_OF_ANCIENT_RUNES":29.0,
   "MUGGLE_STUDY":58.0,
   "ANCIENT_STUDIES":60.0,
   "ADVANCED_ARITHMANCY_STUDIES":79.0,
   "SPELLS":65.0,
   "HERBOLOGY":28.0,
   "HISTORY_OF_MAGIC":28.0,
   "DEFAULT":0.0,
   "POTIONS":44.0,
   "THEORY_OF_MAGIC":50.0,
   "TRANSFIGURATION":11.0,
   "CARE_OF_MAGICAL_CREATURES":11.0
  }
 }
}