{
 "TEST_REGISTRATION":"BFPZ87456768490017",
 "NOTEBOOK":"YELLOW",
 "STUDENT_DATA":{
  "NAME":"Petter Jenssen",
  "GENDER":"M",
  "RACE":"WIZARD",
  "BIRTHDAY":"1988-03-25",
  "AGE":"33",
  "CIVIL_STATUS":"MARRIED",
  "PHONE":"98340130",
  "OCCUPATION":"STUDENT",
  "NU_IDENTIFICATION":"03014304761",
  "MAILER":"pett03014304@gmail.com",
  "PATRONUS":"GERMAN BLACK BEE",
  "WAND":"FINGERNAIL OF RABBIT"
 },
 "SCHOOL_DATA":{
  "SCHOOL_REGISTRATION":"CPKY35147874581437",
  "SCHOOL":"DURMSTRANG",
  "COUNTRY":"NORWAY",
  "HOUSES":"SPHYNXOND"
 },
 "EXAM_DATA":{
  "MEDIA":1097.62,
  "SUBJECTS":{
   "DIVINATION":69.0,
   "ALCHEMY":28.0,
   "APPARITION":37.0,
   "ARITHMANCY":22.0,
   "MUGGLE_ART":37.0,
   "DARK_ARTS":57.0,
   "ASTRONOMY":36.0,
   "DEFENSE_AGAINST_THE_DARK_ARTS":20.0,
   "STUDY_OF_ANCIENT_RUNES":46.0,
   "MUGGLE_STUDY":55.0,
   "ANCIENT_STUDIES":85.0,
   "ADVANCED_ARITHMANCY_STUDIES":5.0,
   "SPELLS":73.0,
   "HERBOLOGY":100.0,
   "HISTORY_OF_MAGIC":69.0,
   "DEFAULT":74.0,
   "POTIONS":97.0,
   "THEORY_OF_MAGIC":91.0,
   "TRANSFIGURATION":41.0,
   "CARE_OF_MAGICAL_CREATURES":55.0
  }
 }
}