{
 "TEST_REGISTRATION":"URLX58264888015463",
 "NOTEBOOK":"BLUE",
 "STUDENT_DATA":{
  "NAME":"Jessica Rice",
  "GENDER":"F",
  "RACE":"MESTIZOS",
  "BIRTHDAY":"2004-02-18",
  "AGE":"17",
  "CIVIL_STATUS":"SINGLE",
  "PHONE":"(981)379-5378x31840",
  "OCCUPATION":"Financial controller",
  "NU_IDENTIFICATION":"551-15-6170",
  "MAILER":"jes551-15-61@yahoo.com",
  "PATRONUS":"WELDER",
  "WAND":"NOSE OF CATTLE"
 },
 "SCHOOL_DATA":{
  "SCHOOL_REGISTRATION":"AJZD62679157961659",
  "SCHOOL":"HOGWARTS",
  "COUNTRY":"ENGLAND",
  "HOUSES":"HUFFLEPUFF"
 },
 "EXAM_DATA":{
  "MEDIA":813.57,
  "SUBJECTS":{
   "DIVINATION":0.0,
   "ALCHEMY":96.0,
   "APPARITION":28.0,
   "ARITHMANCY":81.0,
   "MUGGLE_ART":38.0,
   "DARK_ARTS":41.0,
   "ASTRONOMY":62.0,
   "DEFENSE_AGAINST_THE_DARK_ARTS":1.0,
   "STUDY_OF_ANCIENT_RUNES":90.0,
   "MUGGLE_STUDY":15.0,
   "ANCIENT_STUDIES":21.0,
   "ADVANCED_ARITHMANCY_STUDIES":3.0,
   "SPELLS":66.0,
   "HERBOLOGY":84.0,
   "HISTORY_OF_MAGIC":16.0,
   "DEFAULT":15.0,
   "POTIONS":26.0,
   "THEORY_OF_MAGIC":28.0,
   "TRANSFIGURATION":14.0,
   "CARE_OF_MAGICAL_CREATURES":96.0
  }
 }
}