{
 "TEST_REGISTRATION":"WCIU67817915619445",
 "NOTEBOOK":"YELLOW",
 "STUDENT_DATA":{
  "NAME":"Christina Elliott",
  "GENDER":"F",
  "BIRTHDAY":"1934-07-31",
  "RACE":"WIZARD",
  "AGE":"87",
  "CIVIL_STATUS":"SINGLE",
  "PHONE":"(065)286-7092x2421",
  "OCCUPATION":"STUDENT",
  "NU_IDENTIFICATION":"349-26-7147",
  "MAILER":"ch349-@yahoo.com",
  "PATRONUS":"CALANCHO\u00ca",
  "WAND":"HAIR OF ANOLE"
 },
 "SCHOOL_DATA":{
  "SCHOOL_REGISTRATION":"TYVQ16383936655396",
  "SCHOOL":"ILVERMORNY",
  "COUNTRY":"EUA",
  "HOUSES":"PUMARUNA"
 },
 "EXAM_DATA":{
  "MEDIA":1236.81,
  "SUBJECTS":{
   "DIVINATION":98.0,
   "ALCHEMY":54.0,
   "APPARITION":76.0,
   "ARITHMANCY":59.0,
   "MUGGLE_ART":42.0,
   "DARK_ARTS":69.0,
   "ASTRONOMY":11.0,
   "DEFENSE_AGAINST_THE_DARK_ARTS":86.0,
   "STUDY_OF_ANCIENT_RUNES":92.0,
   "MUGGLE_STUDY":63.0,
   "ANCIENT_STUDIES":91.0,
   "ADVANCED_ARITHMANCY_STUDIES":77.0,
   "SPELLS":65.0,
   "HERBOLOGY":77.0,
   "HISTORY_OF_MAGIC":86.0,
   "DEFAULT":89.0,
   "POTIONS":29.0,
   "THEORY_OF_MAGIC":25.0,
   "TRANSFIGURATION":26.0,
   "CARE_OF_MAGICAL_CREATURES":80.0
  }
 }
}