{
 "TEST_REGISTRATION":"NWRM92188848418118",
 "NOTEBOOK":"YELLOW",
 "STUDENT_DATA":{
  "NAME":"Niklas Boman",
  "GENDER":"M",
  "RACE":"WIZARD",
  "BIRTHDAY":"1933-12-20",
  "AGE":"88",
  "CIVIL_STATUS":"SINGLE",
  "PHONE":"+46 (0)8 479 879 01",
  "OCCUPATION":"Surveyor, quantity",
  "NU_IDENTIFICATION":"795-50-1801",
  "MAILER":"n7@gmail.com",
  "PATRONUS":"DOGFISH",
  "WAND":"GLANDULA OF NIGHTINGALE"
 },
 "SCHOOL_DATA":{
  "SCHOOL_REGISTRATION":"SVEU61160115058888",
  "SCHOOL":"KOLDOVSTORETZ",
  "COUNTRY":"RUSSIAN",
  "HOUSES":"RED COURT"
 },
 "EXAM_DATA":{
  "MEDIA":1005.67,
  "SUBJECTS":{
   "DIVINATION":38.0,
   "ALCHEMY":15.0,
   "APPARITION":22.0,
   "ARITHMANCY":47.0,
   "MUGGLE_ART":10.0,
   "DARK_ARTS":54.0,
   "ASTRONOMY":89.0,
   "DEFENSE_AGAINST_THE_DARK_ARTS":71.0,
   "STUDY_OF_ANCIENT_RUNES":95.0,
   "MUGGLE_STUDY":51.0,
   "ANCIENT_STUDIES":24.0,
   "ADVANCED_ARITHMANCY_STUDIES":29.0,
   "SPELLS":72.0,
   "HERBOLOGY":79.0,
   "HISTORY_OF_MAGIC":52.0,
   "DEFAULT":16.0,
   "POTIONS":77.0,
   "THEORY_OF_MAGIC":54.0,
   "TRANSFIGURATION":13.0,
   "CARE_OF_MAGICAL_CREATURES":77.0
  }
 }
}