{
 "TEST_REGISTRATION":"DCHJ13196975241186",
 "NOTEBOOK":"BLUE",
 "STUDENT_DATA":{
  "NAME":"Akira Nakatsugawa",
  "GENDER":"M",
  "RACE":"WIZARD",
  "BIRTHDAY":"1930-06-10",
  "AGE":"91",
  "CIVIL_STATUS":"MARRIED",
  "PHONE":"58-4432-1046",
  "OCCUPATION":"Volunteer coordinator",
  "NU_IDENTIFICATION":"048-38-1430",
  "MAILER":"akir0@yahoo.com",
  "PATRONUS":"ANT MAYBE",
  "WAND":"EYE OF OKAPI"
 },
 "SCHOOL_DATA":{
  "SCHOOL_REGISTRATION":"WHJR47397395250475",
  "SCHOOL":"MAHOUTOKORO",
  "COUNTRY":"JAPAN",
  "HOUSES":"HARU"
 },
 "EXAM_DATA":{
  "MEDIA":1035.0,
  "SUBJECTS":{
   "DIVINATION":77.0,
   "ALCHEMY":88.0,
   "APPARITION":68.0,
   "ARITHMANCY":48.0,
   "MUGGLE_ART":91.0,
   "DARK_ARTS":34.0,
   "ASTRONOMY":85.0,
   "DEFENSE_AGAINST_THE_DARK_ARTS":84.0,
   "STUDY_OF_ANCIENT_RUNES":24.0,
   "MUGGLE_STUDY":89.0,
   "ANCIENT_STUDIES":38.0,
   "ADVANCED_ARITHMANCY_STUDIES":43.0,
   "SPELLS":0.0,
   "HERBOLOGY":3.0,
   "HISTORY_OF_MAGIC":34.0,
   "DEFAULT":96.0,
   "POTIONS":52.0,
   "THEORY_OF_MAGIC":43.0,
   "TRANSFIGURATION":0.0,
   "CARE_OF_MAGICAL_CREATURES":42.0
  }
 }
}