{
 "TEST_REGISTRATION":"RNRI21793151918135",
 "NOTEBOOK":"YELLOW",
 "STUDENT_DATA":{
  "NAME":"Ana Beatriz Silveira",
  "GENDER":"F",
  "RACE":"HUMANS (MUGGLE)",
  "BIRTHDAY":"1946-06-25",
  "AGE":"75",
  "CIVIL_STATUS":"DIVORCED",
  "PHONE":"090-0283-5161",
  "OCCUPATION":"Psychologist, forensic",
  "NU_IDENTIFICATION":"78423950123",
  "MAILER":"ana784@hotmail.com",
  "PATRONUS":"BLUEBIRD",
  "WAND":"GLANDULA OF SILVER DOLLAR"
 },
 "SCHOOL_DATA":{
  "SCHOOL_REGISTRATION":"GGAB34217956143408",
  "SCHOOL":"CASTELOBRUXO",
  "COUNTRY":"BRAZIL",
  "HOUSES":null
 },
 "EXAM_DATA":{
  "MEDIA":940.71,
  "SUBJECTS":{
   "DIVINATION":76.0,
   "ALCHEMY":68.0,
   "APPARITION":39.0,
   "ARITHMANCY":27.0,
   "MUGGLE_ART":10.0,
   "DARK_ARTS":65.0,
   "ASTRONOMY":59.0,
   "DEFENSE_AGAINST_THE_DARK_ARTS":82.0,
   "STUDY_OF_ANCIENT_RUNES":67.0,
   "MUGGLE_STUDY":18.0,
   "ANCIENT_STUDIES":55.0,
   "ADVANCED_ARITHMANCY_STUDIES":0.0,
   "SPELLS":9.0,
   "HERBOLOGY":15.0,
   "HISTORY_OF_MAGIC":82.0,
   "DEFAULT":37.0,
   "POTIONS":91.0,
   "THEORY_OF_MAGIC":11.0,
   "TRANSFIGURATION":32.0,
   "CARE_OF_MAGICAL_CREATURES":78.0
  }
 }
}