{
 "TEST_REGISTRATION":"DMFF02939855506056",
 "NOTEBOOK":"BLUE",
 "STUDENT_DATA":{
  "NAME":"Christoffer Lind",
  "GENDER":"M",
  "RACE":"HUMANS (MUGGLE)",
  "BIRTHDAY":"1968-04-01",
  "AGE":"53",
  "CIVIL_STATUS":"WIDOWED",
  "PHONE":"08-683 56 36",
  "OCCUPATION":"Building control surveyor",
  "NU_IDENTIFICATION":"690-05-5848",
  "MAILER":"chri690@yahoo.com",
  "PATRONUS":"SIAMANG",
  "WAND":"GLANDULA OF HAWORTHIA COOPER"
 },
 "SCHOOL_DATA":{
  "SCHOOL_REGISTRATION":"DXKN15441827260905",
  "SCHOOL":"KOLDOVSTORETZ",
  "COUNTRY":"RUSSIAN",
  "HOUSES":"AZURE COURT"
 },
 "EXAM_DATA":{
  "MEDIA":890.0,
  "SUBJECTS":{
   "DIVINATION":100.0,
   "ALCHEMY":67.0,
   "APPARITION":43.0,
   "ARITHMANCY":38.0,
   "MUGGLE_ART":7.0,
   "DARK_ARTS":91.0,
   "ASTRONOMY":13.0,
   "DEFENSE_AGAINST_THE_DARK_ARTS":59.0,
   "STUDY_OF_ANCIENT_RUNES":90.0,
   "MUGGLE_STUDY":32.0,
   "ANCIENT_STUDIES":75.0,
   "ADVANCED_ARITHMANCY_STUDIES":1.0,
   "SPELLS":44.0,
   "HERBOLOGY":26.0,
   "HISTORY_OF_MAGIC":100.0,
   "DEFAULT":5.0,
   "POTIONS":10.0,
   "THEORY_OF_MAGIC":60.0,
   "TRANSFIGURATION":28.0,
   "CARE_OF_MAGICAL_CREATURES":0.0
  }
 }
}