{
 "TEST_REGISTRATION":"ODTO51199891545383",
 "NOTEBOOK":"YELLOW",
 "STUDENT_DATA":{
  "NAME":"Alexia Cardoso",
  "GENDER":"F",
  "RACE":"WIZARD",
  "BIRTHDAY":"1948-11-25",
  "AGE":"73",
  "CIVIL_STATUS":"MARRIED",
  "PHONE":"080-0265-6273",
  "OCCUPATION":"STUDENT",
  "NU_IDENTIFICATION":"02465178326",
  "MAILER":"al02465@hotmail.com",
  "PATRONUS":"CRICKET",
  "WAND":"LIVER OF CHAMOIS"
 },
 "SCHOOL_DATA":{
  "SCHOOL_REGISTRATION":"JFFU33985526318072",
  "SCHOOL":"CASTELOBRUXO",
  "COUNTRY":"BRAZIL",
  "HOUSES":null
 },
 "EXAM_DATA":{
  "MEDIA":1126.57,
  "SUBJECTS":{
   "DIVINATION":33.0,
   "ALCHEMY":18.0,
   "APPARITION":4.0,
   "ARITHMANCY":53.0,
   "MUGGLE_ART":91.0,
   "DARK_ARTS":30.0,
   "ASTRONOMY":100.0,
   "DEFENSE_AGAINST_THE_DARK_ARTS":93.0,
   "STUDY_OF_ANCIENT_RUNES":84.0,
   "MUGGLE_STUDY":6.0,
   "ANCIENT_STUDIES":8.0,
   "ADVANCED_ARITHMANCY_STUDIES":89.0,
   "SPELLS":67.0,
   "HERBOLOGY":14.0,
   "HISTORY_OF_MAGIC":57.0,
   "DEFAULT":62.0,
   "POTIONS":61.0,
   "THEORY_OF_MAGIC":83.0,
   "TRANSFIGURATION":91.0,
   "CARE_OF_MAGICAL_CREATURES":96.0
  }
 }
}